{
    "title": "inter;italic;600;100%;U+0-10FFFF",
    "content": "{\"fontFamily\":\"Inter\",\"fontStyle\":\"italic\",\"fontWeight\":\"600\",\"src\":\"http:\/\/localhost:10002\/wp-content\/uploads\/fonts\/UcCM3FwrK3iLTcvneQg7Ca725JhhKnNqk4j1ebLhAm8SrXTcB9xhiJ-Ek-7MeA.woff2\",\"preview\":\"https:\/\/s.w.org\/images\/fonts\/wp-6.7\/previews\/inter\/inter-600-italic.svg\"}",
    "excerpt": "",
    "date": "2025-03-25 11:54:59",
    "modified": "2025-03-25 11:54:59",
    "slug": "interitalic600100u0-10ffff",
    "type": "wp_font_face",
    "status": "publish",
    "categories": [],
    "tags": [],
    "meta": []
}